MANIFEST.in
board_project_issue_view.xml
project_issue_data.xml
project_issue_demo.xml
project_issue_menu.xml
project_issue_view.xml
res_config_view.xml
setup.py
./__init__.py
./__openerp__.py
./project_issue.py
./res_config.py
./report/__init__.py
./report/project_issue_report.py
i18n/ar.po
i18n/bs.po
i18n/ca.po
i18n/cs.po
i18n/da.po
i18n/de.po
i18n/es.po
i18n/es_CR.po
i18n/es_MX.po
i18n/es_VE.po
i18n/fi.po
i18n/fr.po
i18n/he.po
i18n/hr.po
i18n/hu.po
i18n/it.po
i18n/ja.po
i18n/lt.po
i18n/lv.po
i18n/mk.po
i18n/mn.po
i18n/nb.po
i18n/nl.po
i18n/nl_BE.po
i18n/pl.po
i18n/project_issue.pot
i18n/pt.po
i18n/pt_BR.po
i18n/ro.po
i18n/ru.po
i18n/sk.po
i18n/sl.po
i18n/sv.po
i18n/tr.po
i18n/zh_CN.po
i18n/zh_TW.po
images/issue_analysis.jpeg
images/project_issue.jpeg
openerp_project_issue.egg-info/PKG-INFO
openerp_project_issue.egg-info/SOURCES.txt
openerp_project_issue.egg-info/dependency_links.txt
openerp_project_issue.egg-info/requires.txt
openerp_project_issue.egg-info/top_level.txt
report/project_issue_report_view.xml
security/ir.model.access.csv
security/project_issue_security.xml
static/src/img/icon.png
test/cancel_issue.yml
test/issue.eml
test/issue_demo.yml
test/issue_process.yml
test/subscribe_issue.yml